<?xml version="1.0" encoding="UTF-8"?>
<!DOCTYPE document SYSTEM "../../../units/schema/template.dtd">
<document>
	<form action="$params['form_action']" cms:eval="action" method="POST" id="faq_new_question_form">
		<label>
			<span><cms:text constant="label_question" module="faq"/></span>
			<textarea
				class="multi-language"
				name="question"
				style="width: 450px; height: 100px;"
			/>
		</label>
		<label>
			<span><cms:text constant="label_answer" module="faq"/></span>
			<textarea
				class="multi-language"
				name="answer"
				style="width: 450px; height: 100px;"
			/>
		</label>
		<label class="checkbox">
			<input type="checkbox" name="visible" checked="checked"/>
			<span><cms:text constant="label_visible" module="faq"/></span>
		</label>
		<div class="button_bar">
			<button type="submit"><cms:text constant="save"/></button>
			<button type="reset"><cms:text constant="reset"/></button>
		</div>
	</form>
	<script type="text/javascript">
		new LanguageSelector('faq_new_question_form');
	</script>
</document>
