<?xml version="1.0" encoding="UTF-8"?>
<!DOCTYPE document SYSTEM "../../../units/schema/template.dtd">
<document>
	<form action="$params['form_action']" cms:eval="action" method="POST" id="shop_item_change_form">
		<div id="shop_change_item_notebook">
			<div>
				<div class="box left" style="width: 290px;">
					<label>
						<input type="hidden" name="id" value="$params['id']" cms:eval="value"/>
						<span><cms:text constant="label_name" module="shop"/></span>
						<input type="text" class="multi-language" name="name" style="width: 270px;" maxlength="30"/>
						<cms:language_data param="name"/>
					</label>
				</div>
				<div class="box left" style="width: 160px;">
					<label>
						<span><cms:text constant="label_manufacturer" module="shop"/></span>
						<select name="manufacturer" style="width: 160px;">
							<option/>
							<cms:manufacturer_list
								template="manufacturer_option.xml"
								local="1"
								selected="$params['manufacturer']"
								cms:eval="selected"
							/>
						</select>
					</label>
				</div>

				<label style="clear: both; padding-top: 10px;">
					<span><cms:text constant="label_uid" module="shop"/></span>
					<input
						name="uid"
						class="code ltr"
						type="text"
						value="$params['uid']"
						maxlength="13"
						cms:eval="value"
						/>
				</label>

				<label style="clear: both; padding-top: 10px;">
					<span><cms:text constant="label_description" module="shop"/></span>
					<textarea name="description" class="multi-language" style="width: 460px; height: 155px;"/>
					<cms:language_data param="description"/>
				</label>
				<div class="box left" style="width: 120px;">
					<label>
						<span><cms:text constant="label_price" module="shop"/></span>
						<input
							type="text"
							name="price"
							value="$params['price']"
							cms:eval="value"
							style="width: 100px;"
							maxlength="30"
						/>
					</label>
				</div>
				<div class="box left" style="width: 120px;">
					<label>
						<span><cms:text constant="label_size_definition" module="shop"/></span>
						<select name="size_definition" style="width: 200px;">
							<option></option>
							<cms:size_list
								template="size_option.xml"
								local="1"
								selected="$params['size_definition']"
								cms:eval="selected"
							/>
						</select>
					</label>
				</div>
				<div style="clear: both; padding-top: 10px; padding-bottom: 10px;">
					<div class="box left" style="width: 120px;">
						<label>
							<span><cms:text constant="label_tax" module="shop"/></span>
							<input name="tax" value="$params['tax']" style="width: 100px;" cms:eval="value"/>
						</label>
					</div>
					<div class="box left" style="width: 120px;">
						<label>
							<span><cms:text constant="label_weight" module="shop"/></span>
							<input name="weight" value="$params['weight']" style="width: 100px;" cms:eval="value"/>
						</label>
					</div>
					<div class="box left">
						<label>
							<span><cms:text constant="label_priority" module="shop"/></span>
							<input name="priority" value="$params['priority']" style="width: 60px;" cms:eval="value"/>
						</label>
					</div>
				</div>
				<label class="checkbox" cms:tooltip="tooltip_item_visible">
					<span><cms:text constant="label_item_visible" module="shop"/></span>
					<input
						type="checkbox"
						name="visible"
						checked="$params['visible'] ? 'checked' : false"
						cms:optional="checked"
						/>
				</label>
				<div style="clear: both; padding-bottom: 25px;">
					<cms:text constant="message_images_upload" module="shop"/>
				</div>
			</div>

			<div class="scrollable_list">
				<input name="colors" type="hidden" value="$params['colors']" cms:eval="value"/>
				<label class="inline">
					<span><cms:text constant="label_color_value" module="shop"/></span>
					<input name="color_value" class="code" type="color" style="width: 60px"/>
				</label>
				<label class="inline">
					<span><cms:text constant="label_color_name" module="shop"/></span>
					<input name="color_name" type="text"/>
					<button type="button" onclick="javascript: Caracal.Shop.add_color();">
						<cms:text constant="add"/>
					</button>
				</label>
				<div class="list_header">
					<span class="column" style="width: 250px;">
						<cms:text constant="column_color_name" module="shop"/>
					</span>
					<span class="column" style="width: 100px;">
						<cms:text constant="column_color_value" module="shop"/>
					</span>
					<span class="column">
						<cms:text constant="column_options"/>
					</span>
				</div>
				<div class="list_content" style="height: 415px" id="color_list">
				</div>
			</div>

			<div class="scrollable_list">
				<div class="list_header">
					<cms:text constant="label_categories" module="shop"/>
				</div>
				<div class="list_content" style="height: 480px">
					<cms:category_list
						template="category_checkbox_list_item.xml"
						local="1"
						item_id="$params['id']"
						cms:eval="item_id"
					/>
				</div>
			</div>

			<div class="scrollable_list">
				<label class="inline">
					<span><cms:text constant="label_search_query" module="shop"/></span>
					<input name="search_query" type="text"/>
					<button
						type="button"
						onclick="javascript: Caracal.Shop.open_item_search();"
					>
						<cms:text constant="search"/>
					</button>
				</label>
				<div class="list_header">
					<span class="column" style="width: 250px;">
						<cms:text constant="column_name" module="shop"/>
					</span>
					<span class="column" style="width: 60px;">
						<cms:text constant="column_price" module="shop"/>
					</span>
					<span class="column" style="width: 50px;">
						<cms:text constant="column_rating" module="shop"/>
					</span>
					<span class="column">
						<cms:text constant="column_options"/>
					</span>
				</div>
				<div class="list_content" style="height: 440px" id="related_items">
					<cms:item_list
						related="$params['id']"
						cms:eval="related"
						template="item_list_option.xml"
						local="1"
					/>
				</div>
			</div>

			<div class="scrollable_list">
				<div class="list_header">
					<span class="column" style="width: 360px;">
						<cms:text constant="column_name_and_price" module="shop"/>
					</span>
				</div>
				<div class="list_content" style="height: 370px" id="related_items">
					<cms:delivery_methods
						template="item_delivery_list.xml"
						local="1"
						item="$params['id']"
						cms:eval="item"
					/>
				</div>
			</div>
		</div>

		<div class="button_bar">
			<button type="submit"><cms:text constant="save"/></button>
			<button type="reset"><cms:text constant="reset"/></button>
			<button type="button" onclick="$params['cancel_action']" cms:eval="onclick">
				<cms:text constant="cancel"/>
			</button>
		</div>
	</form>
	<script type="text/javascript">
		var backend_url = window.location.protocol + '//' + window.location.host + window.location.pathname;
		var selector = new LanguageSelector('shop_item_change_form');
		var notebook = new Notebook('shop_change_item_notebook');

		notebook
			.setPageTitle(0, language_handler.getText('shop', 'tab_item'))
			.setPageTitle(1, language_handler.getText('shop', 'tab_colors'))
			.setPageTitle(2, language_handler.getText('shop', 'tab_category'))
			.setPageTitle(3, language_handler.getText('shop', 'tab_related'))
			.setPageTitle(4, language_handler.getText('shop', 'tab_delivery'));

		// add colors
		Caracal.Shop.parse_colors();

		// create toolbar
		toolbar_api
				.createToolbar('shop_item_change_form', '[name=description]:input')
				.addControl('common', 'markdown')
				.addControl('gallery', 'article_image')
				.addControl('downloads', 'link');
	</script>
</document>
